{
    "rct_anchors": [
        {
            "nct_id": "NCT03333333",
            "intervention": "Statin",
            "hr": 0.81,
            "n": 10000,
            "age_mean": 62,
            "age_std": 10,
            "label_quality": 1.0
        },
        {
            "nct_id": "NCT04444444",
            "intervention": "Statin",
            "hr": 0.83,
            "n": 5000,
            "age_mean": 65,
            "age_std": 8,
            "label_quality": 1.0
        }
    ],
    "observational_ihme": [
        {
            "location": "USA",
            "hr_obs": 0.85,
            "n": 100000,
            "age_mean": 64,
            "age_std": 12,
            "label_quality": 0.7
        },
        {
            "location": "IND",
            "hr_obs": 0.78,
            "n": 200000,
            "age_mean": 55,
            "age_std": 15,
            "label_quality": 0.6
        },
        {
            "location": "CHN",
            "hr_obs": 0.82,
            "n": 150000,
            "age_mean": 60,
            "age_std": 11,
            "label_quality": 0.65
        },
        {
            "location": "NGA",
            "hr_obs": 0.75,
            "n": 50000,
            "age_mean": 52,
            "age_std": 14,
            "label_quality": 0.5
        }
    ],
    "context_wb": [
        {
            "location": "USA",
            "gdp": 76000,
            "uhc": 85
        },
        {
            "location": "IND",
            "gdp": 2400,
            "uhc": 47
        },
        {
            "location": "CHN",
            "gdp": 12500,
            "uhc": 70
        },
        {
            "location": "NGA",
            "gdp": 2100,
            "uhc": 38
        }
    ]
}